LICENSE
README.md
setup.cfg
setup.py
tf_helpers/__init__.py
tf_helpers.egg-info/PKG-INFO
tf_helpers.egg-info/SOURCES.txt
tf_helpers.egg-info/dependency_links.txt
tf_helpers.egg-info/requires.txt
tf_helpers.egg-info/top_level.txt
tf_helpers/training/__init__.py
tf_helpers/training/layers.py
tf_helpers/visu/__init__.py
tf_helpers/visu/colorful_tensors.py
tf_helpers/visu/confusion_matrix.py