Metadata-Version: 2.1
Name: tf-helpers
Version: 0.0.2
Summary: A collection of useful functions for TensorFlow for training and visualization.
Home-page: https://github.com/ltriess/tf_helpers
Author: Larissa Triess
Author-email: mail@triess.eu
License: MIT
Platform: UNKNOWN
Requires-Python: >=3.5
Provides-Extra: tf
Provides-Extra: tf_gpu
